neurosymbols/__init__.py
neurosymbols/core.py
neurosymbols/discovery.py
neurosymbols/extraction.py
neurosymbols/induction.py
neurosymbols/logic.py
neurosymbols/pipeline.py
neurosymbols/schema.py
neurosymbols/utils.py
neurosymbols-0.0.1.dist-info/METADATA
neurosymbols-0.0.1.dist-info/WHEEL
neurosymbols-0.0.1.dist-info/licenses/LICENSE
neurosymbols-0.0.1.dist-info/RECORD
